{
    "resourceType": "OrganizationAffiliation", 
    "type": "OrganizationAffiliation", 
    "meta": {
        "tag": [
            {
                "system": "http://terminology.hl7.org/CodeSystem/v3-ActReason", 
                "code": "HTEST", 
                "display": "test health data"
            }
        ]
    }, 
    "implicitRules": "Property. Model:'https://raw.githubusercontent.com/agaldemas/incubated/master/SMARTHEALTH/HL7/FHIR-R4/FHIR-R4/uri' String of characters used to identify a name or a resource", 
    "_implicitRules": {
        "id": "1502d709-55bd-4194-b40b-b9cfe9ad8374"
    }, 
    "language": "Property. Model:'https://raw.githubusercontent.com/agaldemas/incubated/master/SMARTHEALTH/HL7/FHIR-R4/FHIR-R4/code' A string which has at least one character and no leading or trailing whitespace and where there is no whitespace other than single spaces in the contents", 
    "_language": {
        "id": "e9e6ceda-5e5a-4947-a861-f4a5647042cb"
    }, 
    "text": {
        "status": "generated", 
        "div": "<div xmlns=\"http://www.w3.org/1999/xhtml\">\n\t\t\t<p>\n\t\t\t\tHL7 Payer Network services for Acme Hospital from 1-Jan 2012 to 31-Mar 2012\n\t\t\t</p>\n\t\t</div>"
    }, 
    "extension": [
        "urn:ngsi-ld:Extension:001"
    ], 
    "modifierExtension": [
        "urn:ngsi-ld:Extension:modifier001"
    ], 
    "identifier": [
        {
            "system": "http://www.acme.org/practitioners", 
            "value": "23"
        }
    ], 
    "active": true, 
    "_active": {
        "id": "aeab97b8-726f-4b9f-a90a-44e251946ad2"
    }, 
    "name": "Property. Model:'https://raw.githubusercontent.com/agaldemas/incubated/master/SMARTHEALTH/HL7/FHIR-R4/FHIR-R4/string' A sequence of Unicode characters", 
    "_name": {
        "id": "ff4499cc-40e4-409f-b5f8-94e9c5842582"
    }, 
    "alias": [
        "Property. Model:'https://raw.githubusercontent.com/agaldemas/incubated/master/SMARTHEALTH/HL7/FHIR-R4/FHIR-R4/string' A list of alternate names that the organization is known as, or was known as in the past."
    ], 
    "_alias": [
        {
            "id": "07d97431-2cc2-4d9c-a783-4104f08a4aa1"
        }
    ], 
    "telecom": [
        {
            "system": "email", 
            "value": "general.practice@example.org", 
            "use": "work"
        }
    ], 
    "address": [
        {
            "id": "92d60a7a-8eeb-4c71-9e34-a1f8c1b96883", 
            "_use": {
                "id": "b3d57955-6d89-4899-b8df-040269c7db71"
            }, 
            "_type": {
                "id": "6d1916c0-6fcc-4fa9-b712-11f4e198e862"
            }, 
            "text": "Specifies the entire address as it should be displayed e.g. on a postal label. This may be provided instead of or as well as the specific parts.", 
            "_text": {
                "id": "c8fa6932-4bbb-4c95-a180-5c416b6d5440"
            }, 
            "line": [
                "This component contains the house number, apartment number, street name, street direction,  P.O. Box number, delivery hints, and similar address information."
            ], 
            "_line": [
                {
                    "id": "b53b2148-e116-4965-8729-8f0d55e43690"
                }
            ], 
            "city": "The name of the city, town, suburb, village or other community or delivery center.", 
            "_city": {
                "id": "3394d914-2995-4e79-8678-44e7b748e0b1"
            }, 
            "district": "The name of the administrative area (county).", 
            "_district": {
                "id": "3cbd07a7-c8f4-4884-8226-f1de5e401867"
            }, 
            "state": "Sub-unit of a country with limited sovereignty in a federally organized country. A code may be used if codes are in common use (e.g. US 2 letter state codes).", 
            "_state": {
                "id": "c530f64f-52a1-4d2f-8333-516e5388f7a3"
            }, 
            "postalCode": "A postal code designating a region defined by the postal service.", 
            "_postalCode": {
                "id": "f87a21ce-f4f2-4915-89cd-5d36f75ec21e"
            }, 
            "country": "Country - a nation as commonly understood or generally accepted.", 
            "_country": {
                "id": "807455c8-02a4-4f15-b5ea-b2feb1f47d94"
            }, 
            "period": {
                "id": "8b859dce-5852-4298-a26d-f2450e7e6a84", 
                "start": "The start of the period. The boundary is inclusive.", 
                "_start": {
                    "id": "25cfc574-6dee-448b-9d56-81fa0e4c9bc6"
                }, 
                "end": "The end of the period. If the end of the period is missing, it means no end was known or planned at the time the instance was created. The start may be in the past, and the end date in the future, which means that period is expected/planned to end at that time.", 
                "_end": {
                    "id": "dd1fa6ed-71dd-4418-ad3b-9a8b572039db"
                }
            }
        }
    ], 
    "partOf": {
        "id": "8e07237c-a9bf-4c01-bc5b-9db3aa9bcd7d", 
        "reference": "A reference to a location at which the other resource is found. The reference may be a relative reference, in which case it is relative to the service base URL, or an absolute URL that resolves to the location where the resource is found. The reference may be version specific or not. If the reference is not to a FHIR RESTful server, then it should be assumed to be version specific. Internal fragment references (start with '#') refer to contained resources.", 
        "_reference": {
            "id": "41abb0df-530d-471e-93da-a71bc293e94f"
        }, 
        "type": "The expected type of the target of the reference. If both Reference.type and Reference.reference are populated and Reference.reference is a FHIR URL, both SHALL be consistent.\n\nThe type is the Canonical URL of Resource Definition that is the type this reference refers to. References are URLs that are relative to http://hl7.org/fhir/StructureDefinition/ e.g. \"Patient\" is a reference to http://hl7.org/fhir/StructureDefinition/Patient. Absolute URLs are only allowed for logical models (and can only be used in references in logical models, not resources).", 
        "_type": {
            "id": "8001049f-7080-4d8f-8edd-67c95f24e246"
        }, 
        "identifier": {
            "id": "5efed597-9905-428d-8d83-a48139e5c86e", 
            "_use": {
                "id": "71e2e5dd-107c-42ca-87d1-d853d7651b44"
            }, 
            "type": {
                "id": "0dd3a64d-5358-43ff-b1f8-9d8b175a3415", 
                "text": "A human language representation of the concept as seen/selected/uttered by the user who entered the data and/or which represents the intended meaning of the user."
            }, 
            "system": "Establishes the namespace for the value - that is, a URL that describes a set values that are unique.", 
            "_system": {
                "id": "c5b9f630-8908-439a-a2de-19d892f1888d"
            }, 
            "value": "The portion of the identifier typically relevant to the user and which is unique within the context of the system.", 
            "_value": {
                "id": "cd10d55f-dbb0-46a7-9c9f-ab04c0342380"
            }, 
            "period": {
                "id": "51633010-ee3b-4fc3-a80e-07c05dbd2839", 
                "start": "The start of the period. The boundary is inclusive.", 
                "end": "The end of the period. If the end of the period is missing, it means no end was known or planned at the time the instance was created. The start may be in the past, and the end date in the future, which means that period is expected/planned to end at that time."
            }, 
            "assigner": {
                "id": "e3bcf199-45ba-4c98-a4be-189251568de6", 
                "reference": "A reference to a location at which the other resource is found. The reference may be a relative reference, in which case it is relative to the service base URL, or an absolute URL that resolves to the location where the resource is found. The reference may be version specific or not. If the reference is not to a FHIR RESTful server, then it should be assumed to be version specific. Internal fragment references (start with '#') refer to contained resources.", 
                "type": "The expected type of the target of the reference. If both Reference.type and Reference.reference are populated and Reference.reference is a FHIR URL, both SHALL be consistent.\n\nThe type is the Canonical URL of Resource Definition that is the type this reference refers to. References are URLs that are relative to http://hl7.org/fhir/StructureDefinition/ e.g. \"Patient\" is a reference to http://hl7.org/fhir/StructureDefinition/Patient. Absolute URLs are only allowed for logical models (and can only be used in references in logical models, not resources).", 
                "display": "Plain text narrative that identifies the resource in addition to the resource reference."
            }
        }, 
        "display": "Plain text narrative that identifies the resource in addition to the resource reference.", 
        "_display": {
            "id": "02603ec6-17fd-49ca-95a5-7f1627e952a9"
        }
    }, 
    "contact": [
        {
            "id": "a4938a68-6be0-4904-87ba-ae4cbd10cd35", 
            "purpose": {
                "id": "bd08fdcd-fe8b-4425-988a-ec42e9836c20", 
                "coding": [
                    {
                        "id": "840db141-d1cf-4c72-939e-189d840f0819", 
                        "system": "The identification of the code system that defines the meaning of the symbol in the code.", 
                        "version": "The version of the code system which was used when choosing this code. Note that a well-maintained code system does not need the version reported, because the meaning of codes is consistent across versions. However this cannot consistently be assured, and when the meaning is not guaranteed to be consistent, the version SHOULD be exchanged.", 
                        "code": "A symbol in syntax defined by the system. The symbol may be a predefined code or an expression in a syntax defined by the coding system (e.g. post-coordination).", 
                        "display": "A representation of the meaning of the code in the system, following the rules of the system.", 
                        "userSelected": false
                    }
                ], 
                "text": "A human language representation of the concept as seen/selected/uttered by the user who entered the data and/or which represents the intended meaning of the user.", 
                "_text": {
                    "id": "1d4c5b0f-fbbb-460d-b0e7-861b40cee077"
                }
            }, 
            "name": {
                "id": "f8d6a254-4fb6-45cd-9013-bd6657f93b4f", 
                "_use": {
                    "id": "10f2eb2f-a50b-4efa-9f24-8d49654ef489"
                }, 
                "text": "Specifies the entire name as it should be displayed e.g. on an application UI. This may be provided instead of or as well as the specific parts.", 
                "_text": {
                    "id": "3ae62a42-1f69-4ac8-be25-8360ffbeecc0"
                }, 
                "family": "The part of a name that links to the genealogy. In some cultures (e.g. Eritrea) the family name of a son is the first name of his father.", 
                "_family": {
                    "id": "fcdc1704-e90d-47a6-9ea5-2131fa43666a"
                }, 
                "given": [
                    "Given name."
                ], 
                "_given": [
                    {
                        "id": "8f907cbb-9450-4b53-b55b-0a56a7534fc3"
                    }
                ], 
                "prefix": [
                    "Part of the name that is acquired as a title due to academic, legal, employment or nobility status, etc. and that appears at the start of the name."
                ], 
                "_prefix": [
                    {
                        "id": "84b95d65-5038-4c36-a4be-4617359170dd"
                    }
                ], 
                "suffix": [
                    "Part of the name that is acquired as a title due to academic, legal, employment or nobility status, etc. and that appears at the end of the name."
                ], 
                "_suffix": [
                    {
                        "id": "88996fa4-46e3-4604-8c67-8c63c53c5e73"
                    }
                ], 
                "period": {
                    "id": "23aa91c7-d30a-4693-b198-a370c4dd3faf", 
                    "start": "The start of the period. The boundary is inclusive.", 
                    "end": "The end of the period. If the end of the period is missing, it means no end was known or planned at the time the instance was created. The start may be in the past, and the end date in the future, which means that period is expected/planned to end at that time."
                }
            }, 
            "telecom": [
                {
                    "id": "8072f691-7d57-43eb-a75d-f75bec2d9de1", 
                    "_system": {
                        "id": "0ca0c6f3-ac2d-4f65-a1b2-3d473fbe0743"
                    }, 
                    "value": "The actual contact point details, in a form that is meaningful to the designated communication system (i.e. phone number or email address).", 
                    "_value": {
                        "id": "4c725e74-f17e-418a-89f2-c34773700e37"
                    }, 
                    "_use": {
                        "id": "9b371b50-88c6-4a78-a6bd-f915a14d732e"
                    }, 
                    "rank": 123456, 
                    "_rank": {
                        "id": "090226ba-5884-44e7-bbd8-26ec12489c2c"
                    }, 
                    "period": {
                        "id": "6596847e-5e03-43a1-9ef5-fdecb54d1a60", 
                        "start": "The start of the period. The boundary is inclusive.", 
                        "end": "The end of the period. If the end of the period is missing, it means no end was known or planned at the time the instance was created. The start may be in the past, and the end date in the future, which means that period is expected/planned to end at that time."
                    }
                }
            ], 
            "address": {
                "id": "33ce15a2-2da5-43a2-ad81-b7378843c689", 
                "_use": {
                    "id": "0cd5e2b2-d70a-451e-bc44-fff03fcb8994"
                }, 
                "_type": {
                    "id": "dfe889e1-4975-4114-a5e6-c9fc8685bb25"
                }, 
                "text": "Specifies the entire address as it should be displayed e.g. on a postal label. This may be provided instead of or as well as the specific parts.", 
                "_text": {
                    "id": "3f18aea5-ae3b-4a54-93fd-83bd215bbb83"
                }, 
                "line": [
                    "This component contains the house number, apartment number, street name, street direction,  P.O. Box number, delivery hints, and similar address information."
                ], 
                "_line": [
                    {
                        "id": "a283a3ab-3306-45a2-9322-bd08c6f912b2"
                    }
                ], 
                "city": "The name of the city, town, suburb, village or other community or delivery center.", 
                "_city": {
                    "id": "0157dbd8-2f0b-4ef4-bd64-687b8e396f25"
                }, 
                "district": "The name of the administrative area (county).", 
                "_district": {
                    "id": "e0f3d1b4-fe1f-4711-a211-5a3bd6950551"
                }, 
                "state": "Sub-unit of a country with limited sovereignty in a federally organized country. A code may be used if codes are in common use (e.g. US 2 letter state codes).", 
                "_state": {
                    "id": "43ebf838-e185-4119-af28-8b82d62b0d89"
                }, 
                "postalCode": "A postal code designating a region defined by the postal service.", 
                "_postalCode": {
                    "id": "e1ea3044-b818-439b-bc75-b61e9bb4bcf3"
                }, 
                "country": "Country - a nation as commonly understood or generally accepted.", 
                "_country": {
                    "id": "051e853d-cf00-4aae-b6b1-8461328e05e4"
                }, 
                "period": {
                    "id": "4c2c5946-8b32-4b90-8510-622423816188", 
                    "start": "The start of the period. The boundary is inclusive.", 
                    "end": "The end of the period. If the end of the period is missing, it means no end was known or planned at the time the instance was created. The start may be in the past, and the end date in the future, which means that period is expected/planned to end at that time."
                }
            }
        }
    ], 
    "endpoint": [
        {
            "reference": "Endpoint/example"
        }
    ], 
    "hl7Type": [
        {
            "id": "1e63e61e-3943-4efb-8764-cbdb768d2895", 
            "coding": [
                {
                    "id": "aa364af7-d22e-442c-82b5-9568f5b53a53", 
                    "system": "The identification of the code system that defines the meaning of the symbol in the code.", 
                    "_system": {
                        "id": "f2f4ac13-164f-4a94-a85d-93a9eeb9e7bc"
                    }, 
                    "version": "The version of the code system which was used when choosing this code. Note that a well-maintained code system does not need the version reported, because the meaning of codes is consistent across versions. However this cannot consistently be assured, and when the meaning is not guaranteed to be consistent, the version SHOULD be exchanged.", 
                    "_version": {
                        "id": "d1f1a4a5-5ff8-4200-87ea-1a88d2700119"
                    }, 
                    "code": "A symbol in syntax defined by the system. The symbol may be a predefined code or an expression in a syntax defined by the coding system (e.g. post-coordination).", 
                    "_code": {
                        "id": "31b08d4d-be3c-437e-a935-d02f4e809bea"
                    }, 
                    "display": "A representation of the meaning of the code in the system, following the rules of the system.", 
                    "_display": {
                        "id": "6d3be720-5866-44f8-8e9f-febe579b76b3"
                    }, 
                    "userSelected": false, 
                    "_userSelected": {
                        "id": "eb89f1c0-55a4-4635-8ac7-9a59d94c2a9c"
                    }
                }
            ], 
            "text": "A human language representation of the concept as seen/selected/uttered by the user who entered the data and/or which represents the intended meaning of the user.", 
            "_text": {
                "id": "dd2f93d7-38a3-4462-b219-f3eff632ad91"
            }
        }
    ], 
    "id": "urn:ngsi-ld:OrganizationAffiliation:001", 
    "description": "an instance of OrganizationAffiliation"
}