{
  "id": "urn:ngsi-ld:Dataset:id:HUZY:68185655",
  "type": "Dataset",
  "dateCreated": {
    "type": "DateTime",
    "value": "2021-07-01T10:27:49Z"
  },
  "dateModified": {
    "type": "DateTime",
    "value": "2021-07-01T10:27:59Z"
  },
  "source": {
    "type": "Text",
    "value": ""
  },
  "name": {
    "type": "Text",
    "value": "list of open data portals by MELODA.org project"
  },
  "alternateName": {
    "type": "Text",
    "value": ""
  },
  "description": {
    "type": "Text",
    "value": "Analysis based on actual review of the features of the open data portals"
  },
  "dataProvider": {
    "type": "Text",
    "value": "meloda.org"
  },
  "owner": {
    "type": "array",
    "value": [
      "urn:ngsi-ld:Dataset:items:UHNW:18835438",
      "urn:ngsi-ld:Dataset:items:JIFN:75588835"
    ]
  },
  "seeAlso": {
    "type": "array",
    "value": [
      "https://meloda.org"
    ]
  },
  "datasetDescription": {
    "type": "array",
    "value": [
      "List of open data portals",
      "Listado de portales open data"
    ]
  },
  "title": {
    "type": "array",
    "value": [
      "Open Data list",
      "Lista open data"
    ]
  },
  "contactPoint": {
    "type": "array",
    "value": [
      ""
    ]
  },
  "datasetDistribution": {
    "type": "array",
    "value": [
      ""
    ]
  },
  "keyword": {
    "type": "array",
    "value": [
      "opendata",
      "portal"
    ]
  },
  "publisher": {
    "type": "Text",
    "value": "urjc"
  },
  "spatial": {
    "type": "geo:json",
    "value": {
      "type": "Point",
      "coordinates": [
        22.1394715,
        -7.100602
      ]
    }
  },
  "temporal": {
    "type": "array",
    "value": [
      "2021-01-01T00:00:00Z",
      "2021-12-31T23:59:59Z"
    ]
  },
  "theme": {
    "type": "array",
    "value": [
      "data management",
      "open data"
    ]
  },
  "accessRights": {
    "type": "Text",
    "value": "public"
  },
  "creator": {
    "type": "Text",
    "value": "Diego Garcia, Marta Ortiz de Urbina, Carmen de Pablos"
  },
  "documentation": {
    "type": "array",
    "value": [
      "",
      ""
    ]
  },
  "frequency": {
    "type": "array",
    "value": "two years"
  },
  "hasVersion": {
    "type": "Text",
    "value": [
      "",
      ""
    ]
  },
  "identifier": {
    "type": "array",
    "value": [
      "",
      ""
    ]
  },
  "isReferencedBy": {
    "type": "array",
    "value": [
      "urn:ngsi-ld:Dataset:items:HJNK:88711880",
      "urn:ngsi-ld:Dataset:items:MDEO:95193079"
    ]
  },
  "isVersionOf": {
    "type": "array",
    "value": [
      "urn:ngsi-ld:Dataset:items:RBWE:31388012",
      "urn:ngsi-ld:Dataset:items:GATZ:02632837"
    ]
  },
  "landingPage": {
    "type": "array",
    "value": [
      "htps://meloda.org"
    ]
  },
  "language": {
    "type": "array",
    "value": [
      "EN",
      "ES"
    ]
  },
  "otherIdentifier": {
    "type": "array",
    "value": [
      "",
      ""
    ]
  },
  "provenance": {
    "type": "array",
    "value": [
      "",
      ""
    ]
  },
  "qualifiedAttribution": {
    "type": "array",
    "value": [
      ""
    ]
  },
  "qualifiedRelation": {
    "type": "array",
    "value": [
      ""
    ]
  },
  "relatedResource": {
    "type": "array",
    "value": [
      "urn:ngsi-ld:Dataset:items:LGBY:74926949",
      "urn:ngsi-ld:Dataset:items:ZAUC:79968579"
    ]
  },
  "releaseDate": {
    "type": "DateTime",
    "value": "2021-10-01T15:46:46Z"
  },
  "sample": {
    "type": "array",
    "value": [
      "urn:ngsi-ld:Dataset:items:MLHW:64299003",
      "urn:ngsi-ld:Dataset:items:GNXL:59256807"
    ]
  },
  "datasetSource": {
    "type": "array",
    "value": [
      "urn:ngsi-ld:Dataset:items:QTKR:65814062",
      "urn:ngsi-ld:Dataset:items:SVUY:57639613"
    ]
  },
  "spatialResolution": {
    "type": "array",
    "value": [
      864.6
    ]
  },
  "temporalResolution": {
    "type": "array",
    "value": [
      730
    ]
  },
  "datasetType": {
    "type": "Text",
    "value": ""
  },
  "updateDate": {
    "type": "DateTime",
    "value": "2021-07-01T03:37:52Z"
  },
  "version": {
    "type": "Text",
    "value": "3.0"
  },
  "versionNotes": {
    "type": "array",
    "value": [
      "With temporal evolution"
    ]
  },
  "wasGeneratedBy": {
    "type": "Text",
    "value": [
      "meloda Team"
    ]
  }
}


