{
  "id": "urn:ngsi-ld:InfrastructureElement:Production:00155dc09474",
  "type": "InfrastructureElement",
  "domain": "urn:ngsi-ld:Domain:Production",
  "hostname": "continuum-worker-1",
  "internalIpAddress": "192.168.1.35",
  "macAddress": "00:15:5d:c0:94:74",
  "infrastructureElementStatus": "Ready",
  "operatingSystem": "Linux",
  "infrastructureElementTier": "Edge",
  "trustScore": 0.58,
  "containerTechnology": "Kubernetes",
  "lowLevelOrchestrator": "urn:ngsi-ld:LowLevelOrchestrator:Production:Kubernetes",
  "cpuArchitecture": "AMD64",
  "cpuCores": 4,
  "currentCpuUsage": 20.58,
  "ramCapacity": 8192,
  "availableRam": 5100,
  "currentRamUsage": 3092,
  "currentRamUsagePct": 37.7,
  "diskType": "SSD",
  "diskCapacity": 65536,
  "availableDisk": 30585,
  "currentDiskUsage": 34951,
  "currentDiskUsagePct": 53.34,
  "avgPowerConsumption": 110,
  "currentPowerConsumption": 95,
  "realTimeCapable": true,
  "powerSource": "urn:ngsi-ld:PowerSource:Production:SolarFarm01",
  "energyEfficiencyRatio": 0.78,
  "location": {
    "type": "Point",
    "coordinates": [
      -0.3411743020092746,
      39.48103451588121
    ]
  }
}

