{
  "id": "urn:ngsi-ld:Humidifier:fba02151-cd4b-4dfd-a7a7-37dafa66d943",
  "type": "Humidifier",
  "application": {
    "type": "Text",
    "value": "Small Soft Car"
  },
  "internalControl": {
    "type": "Text",
    "value": "mindshare"
  },
  "nominalAirFlowRate": {
    "type": "Measurement",
    "value": {
      "unitCode": "m3/s",
      "observedAt": "2023-01-26T06:41:30Z",
      "value": 0.9292903711390679
    }
  },
  "nominalMoistureGain": {
    "type": "Measurement",
    "value": {
      "unitCode": "kg/s",
      "observedAt": "2023-01-25T15:10:59Z",
      "value": 0.8580622286778447
    }
  },
  "waterRequirement": {
    "type": "Measurement",
    "value": {
      "unitCode": "m3/s",
      "observedAt": "2023-01-26T13:31:51Z",
      "value": 0.554538436027498
    }
  },
  "weight": {
    "type": "Measurement",
    "value": {
      "unitCode": "g",
      "observedAt": "2023-01-26T13:03:34Z",
      "value": 0.7752621626916505
    }
  },
  "isContainedInBuildingSpace": {
    "type": "Relationship",
    "value": "urn:ngsi-ld:BuildingSpace:e921e031-412b-425c-931b-c63634eb5c85"
  },
  "isContainedInPhysicalObject": {
    "type": "Relationship",
    "value": "urn:ngsi-ld:PhysicalObject:013cd1d5-1e31-4a2a-a666-8e18c85a0360"
  },
  "isSubSystemOf": {
    "type": "array",
    "value": [
      {
        "type": "Relationship",
        "value": "urn:ngsi-ld:System:ea1d1a76-356e-491c-b5dc-17a8c456d7f7"
      },
      {
        "type": "Relationship",
        "value": "urn:ngsi-ld:System:f7b44810-8762-4e67-b4d0-6e4d9bb81b46"
      },
      {
        "type": "Relationship",
        "value": "urn:ngsi-ld:System:88bb7831-63c5-40bc-8349-7cef821db39c"
      }
    ]
  },
  "hasManufacturer": {
    "type": "Text",
    "value": "Humidifier Company Inc."
  },
  "hasModel": {
    "type": "Text",
    "value": "Humidifier 0.1.2"
  },
  "dateCreated": {
    "type": "DateTime",
    "value": "2023-01-26T08:47:34.1843489+01:00"
  },
  "dateModified": {
    "type": "DateTime",
    "value": "2023-01-26T06:27:14.5040882+01:00"
  },
  "source": {
    "type": "Text",
    "value": "Import"
  },
  "name": {
    "type": "Text",
    "value": "Humidifier"
  },
  "alternateName": {
    "type": "Text",
    "value": "Humidifier type 2"
  },
  "description": {
    "type": "Text",
    "value": "Humidifier of limited Humidifier types"
  },
  "dataProvider": {
    "type": "Text",
    "value": "IFC file"
  }
}